---
title: JVM 类文件结构与字节码深度解析
date: 2026-05-12 10:15:00+08:00
updated: '2026-05-12T10:15:00+08:00'
description: 面试高频问题：Class 文件的结构？字节码指令有哪些？类加载的过程？ Java 的"一次编写，到处运行"依赖于 Class 文件这一中间格式。理解 Class 文件结构和字节码指令，是深入理解 JVM 的基础，也是性能调优、代码生成、字节码增强等技术的前提。
  常量池是 Class 文件中最大的数据。
topic: java-spring
level: intermediate
status: maintained
tags:
- JVM
- bytecode
- classfile
- jvm-instructions
categories:
- Java 与 Spring
draft: false
---

> 面试高频问题：Class 文件的结构？字节码指令有哪些？类加载的过程？

## 引言

Java 的"一次编写，到处运行"依赖于 Class 文件这一中间格式。理解 Class 文件结构和字节码指令，是深入理解 JVM 的基础，也是性能调优、代码生成、字节码增强等技术的前提。

## 一、Class 文件结构

### 1.1 整体结构

```
┌──────────────────────────────────────────────┐
│              ClassFile 结构                    │
├──────────────────────────────────────────────┤
│  magic（魔数）                               │
│  minor_version（次版本号）                    │
│  major_version（主版本号）                    │
│  constant_pool_count（常量池计数）            │
│  constant_pool（常量池）                      │
│  access_flags（访问标志）                     │
│  this_class（当前类）                         │
│  super_class（父类）                          │
│  interfaces_count + interfaces（接口）        │
│  fields_count + fields（字段）                │
│  methods_count + methods（方法）              │
│  attributes_count + attributes（属性）        │
└──────────────────────────────────────────────┘
```

### 1.2 魔数与版本号

```java
// 魔数：0xCAFEBABE（咖啡宝贝）
// 每个 Class 文件开头都是这个
CA FE BA BE 00 00 00 37  // Java 55 (JDK 11)

// 版本号对应关系
// JDK 1.1 → 45
// JDK 1.2 → 46
// JDK 1.5 → 49
// JDK 1.8 → 52
// JDK 9   → 53
// JDK 11  → 55
// JDK 17  → 61
// JDK 21  → 65
```

### 1.3 常量池

常量池是 Class 文件中最大的数据项，存储字面量和符号引用。

**常量池项目类型**：

| 常量类型 | 值 | 说明 |
|---------|-----|------|
| `CONSTANT_Utf8` | 1 | UTF-8 编码字符串 |
| `CONSTANT_Integer` | 3 | int 型字面量 |
| `CONSTANT_Float` | 4 | float 型字面量 |
| `CONSTANT_Long` | 5 | long 型字面量 |
| `CONSTANT_Double` | 6 | double 型字面量 |
| `CONSTANT_Class` | 7 | 类或接口的符号引用 |
| `CONSTANT_String` | 8 | String 型字面量 |
| `CONSTANT_Fieldref` | 9 | 字段的符号引用 |
| `CONSTANT_Methodref` | 10 | 方法的符号引用 |
| `CONSTANT_InterfaceMethodref` | 11 | 接口方法的符号引用 |
| `CONSTANT_NameAndType` | 12 | 名称和类型的符号引用 |
| `CONSTANT_MethodHandle` | 15 | 方法句柄 |
| `CONSTANT_MethodType` | 16 | 方法类型 |
| `CONSTANT_InvokeDynamic` | 18 | 动态调用点 |

### 1.4 访问标志

| 标志名 | 值 | 说明 |
|--------|-----|------|
| ACC_PUBLIC | 0x0001 | public |
| ACC_FINAL | 0x0010 | final |
| ACC_SUPER | 0x0020 | 使用 invokespecial |
| ACC_INTERFACE | 0x0200 | 接口 |
| ACC_ABSTRACT | 0x0400 | abstract |
| ACC_SYNTHETIC | 0x1000 | 编译器生成 |
| ACC_ANNOTATION | 0x2000 | 注解 |
| ACC_ENUM | 0x4000 | 枚举 |

### 1.5 实战：查看 Class 文件

```bash
# 编译
javac Hello.java

# 查看字节码
javap -v Hello.class

# 常用选项
javap -c        # 反编译字节码指令
javap -p        # 显示私有成员
javap -verbose  # 详细信息（含常量池）
```

**示例输出**：
```
Classfile /Hello.class
  Last modified 2026-05-12; size 400 bytes
  MD5 checksum abc123
  Compiled from "Hello.java"
public class Hello
  minor version: 0
  major version: 55
  flags: ACC_PUBLIC, ACC_SUPER
Constant pool:
   #1 = Methodref          #6.#15     // java/lang/Object."<init>":()V
   #2 = Fieldref           #16.#17    // java/lang/System.out:Ljava/io/PrintStream;
   #3 = String             #18        // Hello World
   #4 = Methodref          #19.#20    // java/io/PrintStream.println:(Ljava/lang/String;)V
   #5 = Class              #21        // Hello
  ...
{
  public Hello();
    descriptor: ()V
    flags: ACC_PUBLIC
    Code:
      stack=1, locals=1, args_size=1
         0: aload_0
         1: invokespecial #1  // Method java/lang/Object."<init>":()V
         4: return
}
```

## 二、字节码指令

### 2.1 指令分类

| 类型 | 指令 | 说明 |
|------|------|------|
| **加载与存储** | aload、iload、astore、istore | 局部变量 ↔ 操作数栈 |
| **算术** | iadd、isub、imul、idiv | 算术运算 |
| **类型转换** | i2l、i2f、l2d | 基本类型转换 |
| **对象操作** | new、getfield、putfield | 对象创建与访问 |
| **方法调用** | invokevirtual、invokestatic | 方法调用 |
| **数组操作** | newarray、iaload、iastore | 数组操作 |
| **控制流** | ifeq、goto、tableswitch | 条件跳转 |
| **返回** | return、ireturn、areturn | 方法返回 |
| **异常** | athrow | 抛出异常 |
| **同步** | monitorenter、monitorexit | 加锁/解锁 |

### 2.2 加载与存储指令

```java
// 局部变量 → 操作数栈
iload     // int 型
lload     // long 型
fload     // float 型
dload     // double 型
aload     // 对象引用

// 操作数栈 → 局部变量
istore    // int 型
lstore    // long 型
fstore    // float 型
dstore    // double 型
astore    // 对象引用

// 常量 → 操作数栈
iconst_0  // int 0
iconst_1  // int 1
iconst_5  // int 5
bipush    // byte (-128~127)
sipush    // short (-32768~32767)
ldc       // int / float / String
```

### 2.3 方法调用指令

| 指令 | 说明 | 示例 |
|------|------|------|
| `invokevirtual` | 虚方法（多态）| 实例方法调用 |
| `invokestatic` | 静态方法 | `Math.max()` |
| `invokespecial` | 特殊方法 | 构造函数、private、super |
| `invokeinterface` | 接口方法 | 通过接口引用调用 |
| `invokedynamic` | 动态调用 | Lambda、方法引用 |

**示例**：
```java
// Java 代码
public class Demo {
    public void test() {
        System.out.println("hello");  // invokevirtual
        Math.max(1, 2);              // invokestatic
        new Object();                 // invokespecial
        Runnable r = () -> {};        // invokedynamic
    }
}
```

### 2.4 字节码实战

**示例 1：i++ vs ++i**

```java
// i++
public void incrementPost() {
    int i = 0;
    i++;
}

// 字节码
0: iconst_0      // 将 0 压入操作数栈
1: istore_1      // 存入局部变量表 slot 1（i = 0）
2: iload_1       // 加载 i 到操作数栈
3: iinc          1, 1  // 局部变量表 slot 1 加 1
6: return

// ++i
public void incrementPre() {
    int i = 0;
    ++i;
}

// 字节码
0: iconst_0
1: istore_1
2: iinc          1, 1  // 局部变量表 slot 1 加 1（先加）
5: iload_1       // 加载 i 到操作数栈（后加载）
6: return
```

**示例 2：synchronized 字节码**

```java
// Java 代码
public void syncMethod() {
    synchronized (this) {
        count++;
    }
}

// 字节码
0: aload_0                     // 加载 this
1: dup                         // 复制引用
2: astore_1                    // 存入临时变量
3: monitorenter                // 加锁
4: aload_0                     // 加载 this
5: dup                         // 复制
6: getfield      #2            // 读取 count
9: iconst_1                    // 常量 1
10: iadd                       // 加 1
11: putfield     #2            // 写回 count
14: aload_1                    // 加载临时变量
15: monitorexit                // 解锁（正常路径）
16: goto          24           // 跳转到 return
19: astore_2                   // 异常处理
20: aload_1                    // 加载临时变量
21: monitorexit                // 解锁（异常路径）
22: aload_2                    // 重新抛出异常
23: athrow
24: return
```

**关键**：synchronized 有两个 monitorexit（正常 + 异常路径），确保锁一定会释放。

### 2.5 Lambda 的字节码

```java
// Java 代码
public void lambdaDemo() {
    Runnable r = () -> System.out.println("hello");
    r.run();
}

// 字节码
0: invokedynamic #2, 0  // InvokeDynamic Runnable.run:()V
5: astore_1
6: aload_1
7: invokeinterface #3, 1  // InterfaceMethod Runnable.run:()V
12: return

// Lambda 体编译为私有静态方法
private static void lambda$lambdaDemo$0() {
    System.out.println("hello");
}
```

## 三、栈帧结构

### 3.1 栈帧组成

```
┌──────────────────────────────────────────────┐
│                  栈帧                         │
├──────────────────────────────────────────────┤
│  局部变量表（Local Variable Table）           │
│  ┌────┬────┬────┬────┬────┐              │
│  │slot0│slot1│slot2│slot3│ ... │              │
│  │this│arg1│arg2│var1│var2│              │
│  └────┴────┴────┴────┴────┘              │
│                                              │
│  操作数栈（Operand Stack）                    │
│  ┌────┬────┬────┐                         │
│  │val1│val2│val3│                         │
│  └────┴────┴────┘                         │
│                                              │
│  动态链接（Dynamic Linking）                  │
│  └─ 指向常量池的方法引用                       │
│                                              │
│  方法返回地址（Return Address）               │
└──────────────────────────────────────────────┘
```

### 3.2 局部变量表

- 存储**方法参数**和**局部变量**
- 以 slot 为单位（32 位类型占 1 slot，64 位占 2 slot）
- 实例方法 slot 0 是 `this`

```java
public void test(int a, long b, String c) {
    int d = 0;
}

// 局部变量表
// slot 0: this
// slot 1: a (int, 1 slot)
// slot 2-3: b (long, 2 slots)
// slot 4: c (String 引用, 1 slot)
// slot 5: d (int, 1 slot)
```

## 四、字节码增强技术

### 4.1 ASM

```java
// ASM：底层字节码操作框架
ClassWriter cw = new ClassWriter(ClassWriter.COMPUTE_MAXS);
cw.visit(V1_8, ACC_PUBLIC, "Hello", null, "java/lang/Object", null);

// 添加字段
FieldVisitor fv = cw.visitField(ACC_PRIVATE, "name", "Ljava/lang/String;", null, null);
fv.visitEnd();

// 添加方法
MethodVisitor mv = cw.visitMethod(ACC_PUBLIC, "getName", "()Ljava/lang/String;", null, null);
mv.visitCode();
mv.visitVarInsn(ALOAD, 0);
mv.visitFieldInsn(GETFIELD, "Hello", "name", "Ljava/lang/String;");
mv.visitInsn(ARETURN);
mv.visitMaxs(1, 1);
mv.visitEnd();

cw.visitEnd();
byte[] bytes = cw.toByteArray();
```

### 4.2 Javassist

```java
// Javassist：高层字节码操作
ClassPool pool = ClassPool.getDefault();
CtClass cc = pool.get("com.example.Hello");

// 添加方法
CtMethod method = CtNewMethod.make(
    "public void hello() { System.out.println(\"Hello\"); }", 
    cc
);
cc.addMethod(method);

// 修改方法体
CtMethod existingMethod = cc.getDeclaredMethod("greet");
existingMethod.insertBefore("{ System.out.println(\"Before\"); }");
existingMethod.insertAfter("{ System.out.println(\"After\"); }");

cc.toClass();
```

### 4.3 应用场景

| 场景 | 工具 |
|------|------|
| AOP | AspectJ、Spring AOP |
| 热部署 | JRebel、HotSwap |
| 性能监控 | SkyWalking、Pinpoint |
| 代码生成 | Lombok、MapStruct |
| 动态代理 | JDK Proxy、CGLIB |

## 五、面试高频问题

### Q1：Class 文件的结构？

**答**：
- 魔数（0xCAFEBABE）
- 版本号
- 常量池
- 访问标志
- 类/父类/接口
- 字段表
- 方法表
- 属性表

### Q2：i++ 和 ++i 的字节码区别？

**答**：
- `i++`：先 iload（加载），再 iinc（加1）
- `++i`：先 iinc（加1），再 iload（加载）
- 单独使用时效果一样，赋值时结果不同

### Q3：invokedynamic 是什么？

**答**：
- Java 7 引入的动态调用指令
- 支持 Lambda 表达式、方法引用
- 运行时动态解析调用点
- 比 invokevirtual 更灵活

### Q4：synchronized 的字节码实现？

**答**：
- 同步代码块：`monitorenter` + `monitorexit`
- 有两个 monitorexit（正常 + 异常），确保锁释放
- 同步方法：`ACC_SYNCHRONIZED` 标志

### Q5：字节码增强有哪些应用？

**答**：
- AOP（Spring）
- 性能监控（SkyWalking）
- 代码生成（Lombok）
- 热部署（JRebel）

## 六、总结

**Class 文件核心要点**：
- **结构**：魔数 → 版本 → 常量池 → 访问标志 → 类信息 → 字段 → 方法 → 属性
- **常量池**：存储字面量和符号引用
- **字节码指令**：加载、算术、类型转换、对象操作、方法调用、控制流

**方法调用指令**：
| 指令 | 用途 |
|------|------|
| invokevirtual | 实例方法（多态）|
| invokestatic | 静态方法 |
| invokespecial | 构造函数、private、super |
| invokeinterface | 接口方法 |
| invokedynamic | Lambda、动态调用 |

**最佳实践**：
1. 使用 `javap -v` 查看字节码
2. 理解字节码有助于理解并发问题
3. 字节码增强是高级技术，需要谨慎使用

---

**下一篇预告**：Spring Boot 自动配置原理深度解析

**参考资料**：
- 《深入理解 Java 虚拟机》- 周志明
- Java 虚拟机规范：https://docs.oracle.com/javase/specs/jvms/se17/html/
- ASM 官方文档：https://asm.ow2.io/
